dtcalc/__init__.py
dtcalc/__main__.py
dtcalc/dtfmt.py
dtcalc/lexeval.py
dtcalc/tokens.py
dtcalc-0.1a3.dist-info/LICENSE.md
dtcalc-0.1a3.dist-info/METADATA
dtcalc-0.1a3.dist-info/WHEEL
dtcalc-0.1a3.dist-info/top_level.txt
dtcalc-0.1a3.dist-info/RECORD
