Metadata-Version: 2.1
Name: dtcalc
Version: 0.1a3
Summary: Find difference between dates and times
Home-page: https://github.com/ju-sh/dtcalc
Author: Julin S
Author-email: 
License: UNKNOWN
Project-URL: Changelog, https://github.com/ju-sh/dtcalc/blob/master/CHANGELOG.md
Project-URL: Issue Tracker, https://github.com/ju-sh/dtcalc/issues
Platform: UNKNOWN
Classifier: Programming Language :: Python :: 3
Classifier: Programming Language :: Python :: 3.7
Classifier: Programming Language :: Python :: 3.8
Classifier: Programming Language :: Python :: 3.9
Classifier: Programming Language :: Python :: 3.10
Requires-Python: >=3.7
